emptylog/__init__.py
emptylog/abstract_logger.py
emptylog/accumulated_data.py
emptylog/call_data.py
emptylog/empty_logger.py
emptylog/loggers_group.py
emptylog/memory_logger.py
emptylog/printing_logger.py
emptylog/protocols.py
emptylog/py.typed
emptylog-0.0.10.dist-info/LICENSE
emptylog-0.0.10.dist-info/METADATA
emptylog-0.0.10.dist-info/WHEEL
emptylog-0.0.10.dist-info/top_level.txt
emptylog-0.0.10.dist-info/RECORD
