Metadata-Version: 2.1
Name: emptylog
Version: 0.0.10
Summary: Mimicking the logger protocol
Author-email: Evgeniy Blinov <zheni-b@yandex.ru>
Project-URL: Source, https://github.com/pomponchik/emptylog
Project-URL: Tracker, https://github.com/pomponchik/emptylog/issues
Keywords: logging,protocols,loggers mocks
Classifier: Operating System :: MacOS :: MacOS X
Classifier: Operating System :: Microsoft :: Windows
Classifier: Operating System :: POSIX
Classifier: Programming Language :: Python :: 3.8
Classifier: Programming Language :: Python :: 3.9
Classifier: Programming Language :: Python :: 3.10
Classifier: Programming Language :: Python :: 3.11
Classifier: Programming Language :: Python :: 3.12
Classifier: Programming Language :: Python :: 3.13
Classifier: License :: OSI Approved :: MIT License
Classifier: Topic :: Software Development :: Libraries
Classifier: Topic :: Software Development :: Testing
Classifier: Topic :: Software Development :: Testing :: Mocking
Classifier: Topic :: Software Development :: Testing :: Unit
Classifier: Topic :: System :: Logging
Classifier: Intended Audience :: Developers
Classifier: Typing :: Typed
Requires-Python: >=3.8
License-File: LICENSE
Requires-Dist: printo>=0.0.5
